bittensor_api/__init__.py
bittensor_api/bittensor_api.py
bittensor_api/subnets/__init__.py
bittensor_api/subnets/SN1/__init__.py
bittensor_api/subnets/SN1/protocol.py
bittensor_api/subnets/SN2/__init__.py
bittensor_api/subnets/SN2/protocol.py
bittensor_api/subnets/SN3/__init__.py
bittensor_api/subnets/SN3/protocol.py
bittensor_api/subnets/SN4/__init__.py
bittensor_api/subnets/SN4/protocol.py
bittensor_api/subnets/SN5/__init__.py
bittensor_api/subnets/SN5/protocol.py
bittensor_api/subnets/core/__init__.py
bittensor_api-0.1.3.dist-info/LICENSE
bittensor_api-0.1.3.dist-info/METADATA
bittensor_api-0.1.3.dist-info/WHEEL
bittensor_api-0.1.3.dist-info/top_level.txt
bittensor_api-0.1.3.dist-info/RECORD
